gitsearch/__init__.py
gitsearch/git_entities.py
gitsearch/git_search.py
gitsearch/output.py
gitsearch_cli-1.0.0.data/scripts/git-search
gitsearch_cli-1.0.0.dist-info/METADATA
gitsearch_cli-1.0.0.dist-info/WHEEL
gitsearch_cli-1.0.0.dist-info/top_level.txt
gitsearch_cli-1.0.0.dist-info/RECORD
