Metadata-Version: 2.1
Name: gitsearch-cli
Version: 1.0.0
Summary: Search git from the command line
Home-page: UNKNOWN
Author: Owen Rumney
Author-email: owen@owenrumney.co.uk
License: UNKNOWN
Platform: UNKNOWN
Classifier: Programming Language :: Python :: 3
Classifier: License :: OSI Approved :: MIT License
Classifier: Operating System :: OS Independent
Requires-Dist: requests (==2.19.1)
Requires-Dist: tabulate (==0.8.2)
